jupyter_ai/__init__.py
jupyter_ai/_version.py
jupyter_ai/config_manager.py
jupyter_ai/extension.py
jupyter_ai/handlers.py
jupyter_ai/history.py
jupyter_ai/models.py
jupyter_ai/auth/identity.py
jupyter_ai/callback_handlers/__init__.py
jupyter_ai/callback_handlers/metadata.py
jupyter_ai/chat_handlers/__init__.py
jupyter_ai/chat_handlers/ask.py
jupyter_ai/chat_handlers/base.py
jupyter_ai/chat_handlers/clear.py
jupyter_ai/chat_handlers/default.py
jupyter_ai/chat_handlers/export.py
jupyter_ai/chat_handlers/fix.py
jupyter_ai/chat_handlers/generate.py
jupyter_ai/chat_handlers/help.py
jupyter_ai/chat_handlers/learn.py
jupyter_ai/completions/__init__.py
jupyter_ai/completions/models.py
jupyter_ai/completions/handlers/__init__.py
jupyter_ai/completions/handlers/base.py
jupyter_ai/completions/handlers/default.py
jupyter_ai/completions/handlers/model_mixin.py
jupyter_ai/config/config_schema.json
jupyter_ai/context_providers/__init__.py
jupyter_ai/context_providers/_learned.py
jupyter_ai/context_providers/base.py
jupyter_ai/context_providers/file.py
jupyter_ai/document_loaders/__init__.py
jupyter_ai/document_loaders/directory.py
jupyter_ai/document_loaders/splitter.py
jupyter_ai/static/jupyternaut.svg
jupyter_ai/tests/__init__.py
jupyter_ai/tests/test_config_manager.py
jupyter_ai/tests/test_context_providers.py
jupyter_ai/tests/test_directory.py
jupyter_ai/tests/test_extension.py
jupyter_ai/tests/test_handlers.py
jupyter_ai/tests/test_identity.py
jupyter_ai/tests/__snapshots__/test_config_manager.ambr
jupyter_ai/tests/completions/__init__.py
jupyter_ai/tests/completions/test_handlers.py
jupyter_ai/tests/static/.hidden_file.pdf
jupyter_ai/tests/static/.hidden_file.txt
jupyter_ai/tests/static/file0.html
jupyter_ai/tests/static/file1.txt
jupyter_ai/tests/static/file2.py
jupyter_ai/tests/static/file3.csv
jupyter_ai/tests/static/file3.xyz
jupyter_ai/tests/static/file4.pdf
jupyter_ai/tests/static/file9.ipynb
jupyter_ai-2.31.5.dist-info/METADATA
jupyter_ai-2.31.5.dist-info/WHEEL
jupyter_ai-2.31.5.dist-info/entry_points.txt
jupyter_ai-2.31.5.dist-info/licenses/LICENSE
jupyter_ai-2.31.5.dist-info/RECORD
